simplebot/__init__.py
simplebot/__main__.py
simplebot/bot.py
simplebot/commands.py
simplebot/filters.py
simplebot/hookspec.py
simplebot/main.py
simplebot/parser.py
simplebot/plugins.py
simplebot/pytestplugin.py
simplebot/utils.py
simplebot/avatars/adaptive-alt.png
simplebot/avatars/adaptive-default.png
simplebot/avatars/blue-alt.png
simplebot/avatars/blue.png
simplebot/avatars/green-alt.png
simplebot/avatars/green.png
simplebot/avatars/purple-alt.png
simplebot/avatars/purple.png
simplebot/avatars/red-alt.png
simplebot/avatars/red.png
simplebot/avatars/simplebot.png
simplebot/avatars/yellow-alt.png
simplebot/avatars/yellow.png
simplebot/builtin/__init__.py
simplebot/builtin/admin.py
simplebot/builtin/cmdline.py
simplebot/builtin/db.py
simplebot/builtin/log.py
simplebot/builtin/settings.py
simplebot/templates/__init__.py
simplebot/templates/help.j2
simplebot-4.2.0.dist-info/LICENSE
simplebot-4.2.0.dist-info/METADATA
simplebot-4.2.0.dist-info/WHEEL
simplebot-4.2.0.dist-info/entry_points.txt
simplebot-4.2.0.dist-info/top_level.txt
simplebot-4.2.0.dist-info/RECORD
