Metadata-Version: 2.2
Name: simplebot
Version: 4.2.0
Summary: SimpleBot: Extensible bot for Delta Chat
Home-page: https://github.com/simplebot-org/simplebot
Author: The SimpleBot Contributors
Author-email: adbenitez@nauta.cu, holger@merlinux.eu
Keywords: deltachat bot email
Classifier: Development Status :: 4 - Beta
Classifier: Intended Audience :: Developers
Classifier: Intended Audience :: System Administrators
Classifier: Intended Audience :: End Users/Desktop
Classifier: License :: OSI Approved :: Mozilla Public License 2.0 (MPL 2.0)
Classifier: Operating System :: POSIX
Classifier: Topic :: Utilities
Classifier: Programming Language :: Python :: 3
Requires-Python: >=3.9
License-File: LICENSE
Requires-Dist: deltachat>=1.142.7
Requires-Dist: py>=1.11.0
Requires-Dist: Pillow>=11.1.0
Requires-Dist: Jinja2>=3.1.5
Provides-Extra: test
Requires-Dist: pytest>=8.2.1; extra == "test"
Requires-Dist: xkcd>=2.4.2; extra == "test"
Requires-Dist: wikiquote>=0.1.17; extra == "test"
Provides-Extra: dev
Requires-Dist: deltachat>=1.142.7; extra == "dev"
Requires-Dist: py>=1.11.0; extra == "dev"
Requires-Dist: Pillow>=11.1.0; extra == "dev"
Requires-Dist: Jinja2>=3.1.5; extra == "dev"
Requires-Dist: pytest>=8.2.1; extra == "dev"
Requires-Dist: xkcd>=2.4.2; extra == "dev"
Requires-Dist: wikiquote>=0.1.17; extra == "dev"
Requires-Dist: black>=24.4.2; extra == "dev"
Requires-Dist: flake8>=7.0.0; extra == "dev"
Requires-Dist: isort>=5.13.2; extra == "dev"
Dynamic: author
Dynamic: author-email
Dynamic: classifier
Dynamic: description
Dynamic: description-content-type
Dynamic: home-page
Dynamic: keywords
Dynamic: provides-extra
Dynamic: requires-dist
Dynamic: requires-python
Dynamic: summary
